<?xml version="1.0" encoding="UTF-8"?><retEnviNFe versao="4.00" xmlns="http://www.portalfiscal.inf.br/nfe"><tpAmb>1</tpAmb><verAplic>SVRSnfce202203151209</verAplic><cStat>104</cStat><xMotivo>Lote processado</xMotivo><cUF>22</cUF><dhRecbto>2022-06-30T10:42:28-03:00</dhRecbto><protNFe versao="4.00"><infProt><tpAmb>1</tpAmb><verAplic>SVRSnfce202203151209</verAplic><chNFe>22220626982672000133650040000002441100002448</chNFe><dhRecbto>2022-06-30T10:42:28-03:00</dhRecbto><nProt>322220110256296</nProt><digVal>aLwfYZICzOf8hjEZGRYabt8BMMA=</digVal><cStat>100</cStat><xMotivo>Autorizado o uso da NF-e</xMotivo></infProt></protNFe></retEnviNFe>